Topsis_Riya_102003451/topsis.py
Topsis_Riya_102003451-0.1.dist-info/METADATA
Topsis_Riya_102003451-0.1.dist-info/WHEEL
Topsis_Riya_102003451-0.1.dist-info/entry_points.txt
Topsis_Riya_102003451-0.1.dist-info/top_level.txt
Topsis_Riya_102003451-0.1.dist-info/RECORD
