Metadata-Version: 2.1
Name: Topsis-Riya-102003451
Version: 0.1
Summary: This is package for topsis of version 0.3
Author: Taruna Jain
Author-email: tjain_be20@thapar.edu
Requires-Dist: pandas
